buf/validate/validate_pb2.py
buf/validate/validate_pb2.pyi
fathom/api/v2/async_pb2.py
fathom/api/v2/async_pb2.pyi
fathom/api/v2/async_pb2_grpc.py
fathom/api/v2/common_pb2.py
fathom/api/v2/common_pb2.pyi
fathom/api/v2/common_pb2_grpc.py
fathom/api/v2/fathom_pb2.py
fathom/api/v2/fathom_pb2.pyi
fathom/api/v2/fathom_pb2_grpc.py
fathom/api/v2/portfolio_pb2.py
fathom/api/v2/portfolio_pb2.pyi
fathom/api/v2/portfolio_pb2_grpc.py
fathom/sdk/__init__.py
fathom/sdk/_internal/__init__.py
fathom/sdk/_internal/common.py
fathom/sdk/_internal/geojson.py
fathom/sdk/_internal/kml.py
fathom/sdk/_internal/vector_file.py
fathom/sdk/client.py
fathom/sdk/clients/__init__.py
fathom/sdk/clients/async_tasks.py
fathom/sdk/clients/geo.py
fathom/sdk/clients/geojson.py
fathom/sdk/clients/portfolio.py
fathom/sdk/clients/vector_file.py
fathom/sdk/common.py
fathom/sdk/exceptions.py
fathom/sdk/v2.py
protoc_gen_openapiv2/options/annotations_pb2.py
protoc_gen_openapiv2/options/annotations_pb2.pyi
protoc_gen_openapiv2/options/openapiv2_pb2.py
protoc_gen_openapiv2/options/openapiv2_pb2.pyi
fathom_global_client_sdk-1.1.1.dist-info/WHEEL
fathom_global_client_sdk-1.1.1.dist-info/METADATA
fathom_global_client_sdk-1.1.1.dist-info/RECORD
