Metadata-Version: 2.1
Name: fathom_global_client_sdk
Author: Fathom
Home-page: https://fathom.global
Classifier: Development Status :: 5 - Production/Stable
Classifier: Intended Audience :: Developers
Classifier: Programming Language :: Python :: 3
Classifier: Programming Language :: Python :: 3.10
Classifier: Programming Language :: Python :: 3.11
Classifier: Programming Language :: Python :: 3.12
Classifier: Programming Language :: Python :: 3.13
Classifier: Typing :: Typed
Requires-Python: >=3.10
Requires-Dist: googleapis-common-protos>=1.63.0,<2
Requires-Dist: grpcio>=1.62.1,<2
Requires-Dist: grpcio-status>=1.62.1,<2
Requires-Dist: protobuf>=5,<6
Requires-Dist: requests>=2,<3
Requires-Dist: fastkml==1.0a11
Requires-Dist: lxml
Requires-Dist: fiona
Requires-Dist: protovalidate
Version: 1.1.1
